VisionTransformer/__init__.py
VisionTransformer/__main__.py
VisionTransformer/config/config.yaml
VisionTransformer/data.py
VisionTransformer/model.py
VisionTransformer/test.py
VisionTransformer/train.py
VisionTransformer/utils.py
vtransformer-0.1.0.dist-info/METADATA
vtransformer-0.1.0.dist-info/WHEEL
vtransformer-0.1.0.dist-info/RECORD
