Metadata-Version: 2.1
Name: vtransformer
Version: 0.1.0
Summary: 
Author: Sashavav
Author-email: vav110011@gmail.com
Requires-Python: >=3.10,<4.0
Classifier: Programming Language :: Python :: 3
Classifier: Programming Language :: Python :: 3.10
Classifier: Programming Language :: Python :: 3.11
Classifier: Programming Language :: Python :: 3.12
Classifier: Programming Language :: Python :: 3.13
Requires-Dist: einops (>=0.8.0,<0.9.0)
Requires-Dist: hydra-core (>=1.3.2,<2.0.0)
Requires-Dist: pre-commit (>=4.0.1,<5.0.0)
Requires-Dist: torch (>=2.5.1,<3.0.0)
Requires-Dist: torchsummary (>=1.5.1,<2.0.0)
Requires-Dist: torchvision (>=0.20.1,<0.21.0)
Requires-Dist: tqdm (>=4.67.1,<5.0.0)
